MANIFEST.in
README.rst
setup.cfg
setup.py
nod2svg/__init__.py
nod2svg/constants.py
nod2svg/main.py
nod2svg.egg-info/PKG-INFO
nod2svg.egg-info/SOURCES.txt
nod2svg.egg-info/dependency_links.txt
nod2svg.egg-info/entry_points.txt
nod2svg.egg-info/requires.txt
nod2svg.egg-info/top_level.txt